flytekitplugins_wandb-1.16.12-py3.14-nspkg.pth
flytekitplugins/wandb/__init__.py
flytekitplugins/wandb/tracking.py
flytekitplugins_wandb-1.16.12.dist-info/METADATA
flytekitplugins_wandb-1.16.12.dist-info/WHEEL
flytekitplugins_wandb-1.16.12.dist-info/namespace_packages.txt
flytekitplugins_wandb-1.16.12.dist-info/top_level.txt
flytekitplugins_wandb-1.16.12.dist-info/RECORD
